Metadata-Version: 2.1
Name: DustyGlow
Version: 0.0.1
Summary: DustyGlow is a standalone python library with Fortran legacy routines for absorption (attenuation) and python scripts for remission of dust in the IR. IMPORTANT: It uses the optically thin limit.
Home-page: https://github.com/neutrinomuon/DustyGlow
Author: Jean Gomes
Author-email: antineutrinomuon@gmail.com
Classifier: Programming Language :: Python :: 3
Classifier: Programming Language :: Fortran
Classifier: Operating System :: OS Independent
License-File: LICENSE.txt
